Metadata-Version: 2.1
Name: Functions-ITA-MVO-41
Version: 0.0.1
Summary: Functions of MVO-41 from T24
Author: Mahmud
Author-email: mahmud.alineto@gmail.com
License: MIT License
Keywords: ITA MVO-41
License-File: LICENSE
